createminecraftserver/__init__.py
createminecraftserver/main.py
createminecraftserver-1.0.dist-info/LICENSE
createminecraftserver-1.0.dist-info/METADATA
createminecraftserver-1.0.dist-info/WHEEL
createminecraftserver-1.0.dist-info/entry_points.txt
createminecraftserver-1.0.dist-info/top_level.txt
createminecraftserver-1.0.dist-info/RECORD
