Metadata-Version: 2.1
Name: createminecraftserver
Version: 1.0
Summary: Create a minecraft server on a Linux OS.
Home-page: https://github.com/Rapha149/CreateMinecraftServer
Author: Rapha149
License: GPL-3.0
Project-URL: Code, https://github.com/Rapha149/CreateMinecraftServer
Project-URL: Issues, https://github.com/Rapha149/CreateMinecraftServer/issues
Keywords: minecraft,server,linux
Platform: UNKNOWN
Classifier: Topic :: Games/Entertainment
Classifier: Topic :: Utilities
Classifier: Development Status :: 4 - Beta
Classifier: License :: OSI Approved :: GNU General Public License v3 (GPLv3)
Classifier: Programming Language :: Python :: 3
Classifier: Programming Language :: Python :: 3.6
Classifier: Operating System :: OS Independent
Classifier: Environment :: Console
Classifier: Intended Audience :: End Users/Desktop
Classifier: Intended Audience :: System Administrators
Classifier: Natural Language :: English
Requires-Python: >=3.6
License-File: LICENSE
Requires-Dist: pathlib
Requires-Dist: pyyaml
Requires-Dist: urllib3
Requires-Dist: packaging
Requires-Dist: nbt (>=1.5.1)
